truffile/__init__.py
truffile/_version.py
truffile/cli.py
truffile/client.py
truffile/schedule.py
truffile/storage.py
truffile/infer/README.md
truffile/infer/__init__.py
truffile/infer/common.py
truffile/infer/prompts.py
truffile/infer/proxy.py
truffile/infer/tooling.py
truffle/__init__.py
truffle/app/__init__.py
truffle/app/app_build_pb2.py
truffle/app/app_build_pb2.pyi
truffle/app/app_build_pb2_grpc.py
truffle/app/app_install_pb2.py
truffle/app/app_install_pb2.pyi
truffle/app/app_install_pb2_grpc.py
truffle/app/app_type_pb2.py
truffle/app/app_type_pb2.pyi
truffle/app/app_type_pb2_grpc.py
truffle/app/background_feed_pb2.py
truffle/app/background_feed_pb2.pyi
truffle/app/background_feed_pb2_grpc.py
truffle/app/background_pb2.py
truffle/app/background_pb2.pyi
truffle/app/background_pb2_grpc.py
truffle/app/curator_pb2.py
truffle/app/curator_pb2.pyi
truffle/app/curator_pb2_grpc.py
truffle/app/default_app_manifest_pb2.py
truffle/app/default_app_manifest_pb2.pyi
truffle/app/default_app_manifest_pb2_grpc.py
truffle/app/foreground_pb2.py
truffle/app/foreground_pb2.pyi
truffle/app/foreground_pb2_grpc.py
truffle/app/system_pb2.py
truffle/app/system_pb2.pyi
truffle/app/system_pb2_grpc.py
truffle/app/task_runtime_pb2.py
truffle/app/task_runtime_pb2.pyi
truffle/app/task_runtime_pb2_grpc.py
truffle/common/__init__.py
truffle/common/content_pb2.py
truffle/common/content_pb2.pyi
truffle/common/content_pb2_grpc.py
truffle/common/file_pb2.py
truffle/common/file_pb2.pyi
truffle/common/file_pb2_grpc.py
truffle/common/icon_pb2.py
truffle/common/icon_pb2.pyi
truffle/common/icon_pb2_grpc.py
truffle/common/led_states_pb2.py
truffle/common/led_states_pb2.pyi
truffle/common/led_states_pb2_grpc.py
truffle/common/tool_provider_pb2.py
truffle/common/tool_provider_pb2.pyi
truffle/common/tool_provider_pb2_grpc.py
truffle/infer/__init__.py
truffle/infer/embedding_pb2.py
truffle/infer/embedding_pb2.pyi
truffle/infer/embedding_pb2_grpc.py
truffle/infer/finishreason_pb2.py
truffile-0.1.8.dist-info/METADATA
truffile-0.1.8.dist-info/WHEEL
truffile-0.1.8.dist-info/entry_points.txt
truffile-0.1.8.dist-info/top_level.txt
truffile-0.1.8.dist-info/RECORD
