Metadata-Version: 2.4
Name: truffile
Version: 0.1.8
Summary: truffile the TruffleOS SDK - Connect and deploy apps to Truffle devices
License: MIT
Requires-Python: >=3.10
Requires-Dist: grpcio>=1.60.0
Requires-Dist: protobuf>=4.25.0
Requires-Dist: httpx>=0.27.0
Requires-Dist: pyyaml>=6.0
Requires-Dist: platformdirs>=3.10.0
Requires-Dist: websockets>=12.0
Requires-Dist: zeroconf>=0.131.0
Provides-Extra: dev
Requires-Dist: pytest>=8.0.0; extra == "dev"
Requires-Dist: grpcio-tools>=1.60.0; extra == "dev"
